setup.py
edbot/EdbotClient.py
edbot/__init__.py
edbot/util.py
edbot.egg-info/PKG-INFO
edbot.egg-info/SOURCES.txt
edbot.egg-info/dependency_links.txt
edbot.egg-info/not-zip-safe
edbot.egg-info/requires.txt
edbot.egg-info/top_level.txt