Metadata-Version: 1.0
Name: edbot
Version: 5.1.4
Summary: Edbot Python API module
Home-page: http://support.ed.bot
Author: Clive Haworth
Author-email: support@ed.bot
License: UNKNOWN
Platform: UNKNOWN
